Workbook

Sheet README
A1: くらしの計算室 — 手取り試算スプレッドシート（2026年版）
A3: 免責事項
A4: ・本テンプレートの計算結果はすべて概算です。最終的な手取り額は給与明細・勤務先の人事・税理士等でご確認ください。
A5: ・健康保険は協会けんぽの標準料率（本人4.95%）を目安にしています。健保組合・扶養家族・標準報酬月額の等級差は反映しません。
A6: ・住民税の天引き開始時期（新卒1年目の非課税期間など）や、各種控除（配偶者・住宅ローン等）は未対応です。
A7: ・ボーナスにも社会保険料率（合計14.65%）を適用します。サイトの無料ツール tools/tedori.html と同一ロジックです。
A8: ・税制・社保料率は改正により変わります。毎年8月頃は料率の見直しを推奨します。
A10: 使い方
A11: 1. 手取り試算シート | B11: B3（月収）・B4（年間ボーナス）を入力すると、社保・税の内訳と毎月の手取り（B17）が自動計算されます。
A12: 2. 手取り比較シート | B12: パターンA〜Cの月収・ボーナスを入力し、手取りとAとの差額（月・年）を横並びで比較できます。転職・昇給の検討に使えます。
A13: 3. 家計サマリシート | B13: 手取り試算の手取りを参照し、固定費・変動費を入力すると「自由に使える額」と貯蓄率がわかります。各費目は自由に書き換えてください。
A14: 4. 積立メモシート | B14: 家計サマリの余剰額を積立額の初期値に、想定利回り・期間から将来の資産額を複利で試算します（tsumitate.html と同一ロジック）。
A15: 5. 年間俯瞰シート | B15: 12か月分の手取り・支出・貯蓄を一覧し、年間合計と累計貯蓄を確認できます。印刷・面談用のサマリです。
A16: 6. 保存・編集 | B16: 数値は自由に書き換えてください。別名で保存すれば、複数シナリオをファイルごとに残せます。
A17: 7. 推奨環境 | B17: 編集はPC版 Excel または Google スプレッドシート（xlsxインポート）を推奨します。スマホは閲覧のみ想定です。
A19: 検証用テストケース
A20: 月収（額面） | B20: 年間ボーナス | C20: 毎月手取り（目安） | D20: 確認方法
A21: 300000 | B21: 0 | C21: 237184 | D21: 手取り比較シートのパターンA初期値
A22: 330000 | B22: 0 | C22: 259827 | D22: 手取り比較シートのパターンB初期値
A23: 360000 | B23: 0 | C23: 282471 | D23: 手取り比較シートのパターンC初期値
A25: 無料Webツール
A26: https://shunsukesaito00.github.io/kurashi/tools/tedori.html
A27: ブラウザで同じ条件を試算できます。共有URLで条件を保存・共有することも可能です。

Sheet 手取り試算
A1: 手取り試算 — くらしの計算室（2026年版）
A2: ※概算です。健保・扶養・住民税の開始時期等は反映しません。給与明細・勤務先でご確認ください。
A3: 月収（額面・円） | B3: 300000
A4: 年間ボーナス（円） | B4: 0
A5: 年間額面 | B5: =B3*12+B4
A6: 健康保険料（月） | B6: =ROUND(B3*0.0495,0)
A7: 厚生年金（月） | B7: =ROUND(B3*0.0915,0)
A8: 雇用保険（月） | B8: =ROUND(B3*0.0055,0)
A9: 社会保険料（年） | B9: =(B6+B7+B8)*12+B4*0.1465
A10: 給与所得控除（年） | B10: =IF(B5<=1625000,550000,IF(B5<=1800000,B5*0.4-100000,IF(B5<=3600000,B5*0.3+80000,IF(B5<=6600000,B5*0.2+440000,IF(B5<=8500000,B5*0.1+1100000,1950000)))))
A11: 課税所得・所得税用（年） | B11: =MAX(0,B5-B10-B9-480000)
A12: 所得税（年・復興含む） | B12: =IF(B11<=0,0,IF(B11<=1950000,B11*0.05,IF(B11<=3300000,B11*0.1-97500,IF(B11<=6950000,B11*0.2-427500,IF(B11<=9000000,B11*0.23-636000,IF(B11<=18000000,B11*0.33-1536000,IF(B11<=40000000,B11*0.4-2796000,B11*0.45-4796000)))))))*1.021
A13: 課税標準・住民税用（年） | B13: =MAX(0,B5-B10-B9-430000)
A14: 住民税（年） | B14: =B13*0.1+5000
A15: 所得税（月割） | B15: =IF(B5=0,0,ROUND(B12/12*(B3*12/B5),0))
A16: 住民税（月割） | B16: =ROUND(B14/12,0)
A17: 毎月の手取り | B17: =B3-B6-B7-B8-B15-B16
A18: 控除合計（月） | B18: =B3-B17
A19: 手取り率 | B19: =IF(B3=0,"",B17/B3)
A20: 年間手取り目安（簡易） | B20: =B17*12

Sheet 手取り比較
A1: 手取り比較（最大3パターン）— くらしの計算室
A2: ※概算です。健保・扶養・住民税の開始時期等は反映しません。給与明細・勤務先でご確認ください。 | B2: パターンA | C2: パターンB | D2: パターンC
A3: 月収（額面・円） | B3: 300000 | C3: 330000 | D3: 360000
A4: 年間ボーナス（円） | B4: 0 | C4: 0 | D4: 0
A5: 年間額面 | B5: =B3*12+B4 | C5: =C3*12+C4 | D5: =D3*12+D4
A6: 健康保険料（月） | B6: =ROUND(B3*0.0495,0) | C6: =ROUND(C3*0.0495,0) | D6: =ROUND(D3*0.0495,0)
A7: 厚生年金（月） | B7: =ROUND(B3*0.0915,0) | C7: =ROUND(C3*0.0915,0) | D7: =ROUND(D3*0.0915,0)
A8: 雇用保険（月） | B8: =ROUND(B3*0.0055,0) | C8: =ROUND(C3*0.0055,0) | D8: =ROUND(D3*0.0055,0)
A9: 社会保険料（年） | B9: =(B6+B7+B8)*12+B4*0.1465 | C9: =(C6+C7+C8)*12+C4*0.1465 | D9: =(D6+D7+D8)*12+D4*0.1465
A10: 給与所得控除（年） | B10: =IF(B5<=1625000,550000,IF(B5<=1800000,B5*0.4-100000,IF(B5<=3600000,B5*0.3+80000,IF(B5<=6600000,B5*0.2+440000,IF(B5<=8500000,B5*0.1+1100000,1950000))))) | C10: =IF(C5<=1625000,550000,IF(C5<=1800000,C5*0.4-100000,IF(C5<=3600000,C5*0.3+80000,IF(C5<=6600000,C5*0.2+440000,IF(C5<=8500000,C5*0.1+1100000,1950000))))) | D10: =IF(D5<=1625000,550000,IF(D5<=1800000,D5*0.4-100000,IF(D5<=3600000,D5*0.3+80000,IF(D5<=6600000,D5*0.2+440000,IF(D5<=8500000,D5*0.1+1100000,1950000)))))
A11: 課税所得・所得税用（年） | B11: =MAX(0,B5-B10-B9-480000) | C11: =MAX(0,C5-C10-C9-480000) | D11: =MAX(0,D5-D10-D9-480000)
A12: 所得税（年・復興含む） | B12: =IF(B11<=0,0,IF(B11<=1950000,B11*0.05,IF(B11<=3300000,B11*0.1-97500,IF(B11<=6950000,B11*0.2-427500,IF(B11<=9000000,B11*0.23-636000,IF(B11<=18000000,B11*0.33-1536000,IF(B11<=40000000,B11*0.4-2796000,B11*0.45-4796000)))))))*1.021 | C12: =IF(C11<=0,0,IF(C11<=1950000,C11*0.05,IF(C11<=3300000,C11*0.1-97500,IF(C11<=6950000,C11*0.2-427500,IF(C11<=9000000,C11*0.23-636000,IF(C11<=18000000,C11*0.33-1536000,IF(C11<=40000000,C11*0.4-2796000,C11*0.45-4796000)))))))*1.021 | D12: =IF(D11<=0,0,IF(D11<=1950000,D11*0.05,IF(D11<=3300000,D11*0.1-97500,IF(D11<=6950000,D11*0.2-427500,IF(D11<=9000000,D11*0.23-636000,IF(D11<=18000000,D11*0.33-1536000,IF(D11<=40000000,D11*0.4-2796000,D11*0.45-4796000)))))))*1.021
A13: 課税標準・住民税用（年） | B13: =MAX(0,B5-B10-B9-430000) | C13: =MAX(0,C5-C10-C9-430000) | D13: =MAX(0,D5-D10-D9-430000)
A14: 住民税（年） | B14: =B13*0.1+5000 | C14: =C13*0.1+5000 | D14: =D13*0.1+5000
A15: 所得税（月割） | B15: =IF(B5=0,0,ROUND(B12/12*(B3*12/B5),0)) | C15: =IF(C5=0,0,ROUND(C12/12*(C3*12/C5),0)) | D15: =IF(D5=0,0,ROUND(D12/12*(D3*12/D5),0))
A16: 住民税（月割） | B16: =ROUND(B14/12,0) | C16: =ROUND(C14/12,0) | D16: =ROUND(D14/12,0)
A17: 毎月の手取り | B17: =B3-B6-B7-B8-B15-B16 | C17: =C3-C6-C7-C8-C15-C16 | D17: =D3-D6-D7-D8-D15-D16
A18: 手取り率 | B18: =IF(B3=0,"",B17/B3) | C18: =IF(C3=0,"",C17/C3) | D18: =IF(D3=0,"",D17/D3)
A19: Aとの手取り差（月） | B19: — | C19: =$C$17-$B$17 | D19: =$D$17-$B$17
A20: Aとの手取り差（年） | B20: — | C20: =C19*12 | D20: =D19*12

Sheet 家計サマリ
A1: 家計サマリ — くらしの計算室
A2: ※概算です。健保・扶養・住民税の開始時期等は反映しません。給与明細・勤務先でご確認ください。
A3: 毎月の手取り（手取り試算より） | B3: ='手取り試算'!B17
A5: 固定費（毎月）
A6: 家賃・住宅ローン | B6: 80000
A7: 水道光熱費 | B7: 12000
A8: 通信費（携帯・ネット） | B8: 8000
A9: 保険（生命・医療等） | B9: 5000
A10: ローン返済（住宅以外） | B10: 0
A11: その他固定費 | B11: 5000
A12: 固定費合計 | B12: =SUM(B6:B11)
A14: 変動費（毎月）
A15: 食費 | B15: 40000
A16: 交通費 | B16: 8000
A17: 日用品・消耗品 | B17: 5000
A18: 交際費・娯楽 | B18: 15000
A19: その他変動費 | B19: 5000
A20: 変動費合計 | B20: =SUM(B15:B19)
A22: 支出合計（固定費＋変動費） | B22: =B12+B20
A23: 自由に使える額（余剰） | B23: =B3-B22
A24: 貯蓄に回せる割合（手取り比） | B24: =IF(B3=0,"",B23/B3)
A25: 支出率（手取り比） | B25: =IF(B3=0,"",B22/B3)
A27: メモ
A28: 自由に使える額は、手取りから固定費・変動費を引いた残りです。実際の貯蓄額は積立・投資の振替額で調整してください。

Sheet 積立メモ
A1: 積立メモ — くらしの計算室
A2: ※概算です。健保・扶養・住民税の開始時期等は反映しません。給与明細・勤務先でご確認ください。
A3: 毎月の積立額（円） | B3: =MAX(0,'家計サマリ'!B23)
A4: 想定利回り（年率%） | B4: 5
A5: 積立期間（年） | B5: 20
A7: シミュレーション結果
A8: 最終的な資産額（目安） | B8: =IF(B5<=0,0,IF(B4=0,ROUND(B3*(B5*12),0),ROUND(B3*(((1+B4/100/12)^(B5*12)-1)/B4/100/12),0)))
A9: 積立元本 | B9: =B3*B5*12
A10: 運用益 | B10: =B8-B9
A11: 元本に対する増加率 | B11: =IF(B9=0,"",B10/B9)
A13: 期間別の目安（上記の積立額・利回りで試算）
A14: 期間（年） | B14: 積立元本 | C14: 資産額（目安）
A15: 10 | B15: =$B$3*A15*12 | C15: =IF(A15<=0,0,IF($B$4=0,ROUND($B$3*(A15*12),0),ROUND($B$3*(((1+$B$4/100/12)^(A15*12)-1)/$B$4/100/12),0)))
A16: 20 | B16: =$B$3*A16*12 | C16: =IF(A16<=0,0,IF($B$4=0,ROUND($B$3*(A16*12),0),ROUND($B$3*(((1+$B$4/100/12)^(A16*12)-1)/$B$4/100/12),0)))
A17: 30 | B17: =$B$3*A17*12 | C17: =IF(A17<=0,0,IF($B$4=0,ROUND($B$3*(A17*12),0),ROUND($B$3*(((1+$B$4/100/12)^(A17*12)-1)/$B$4/100/12),0)))
A19: 無料Webツール
A20: https://shunsukesaito00.github.io/kurashi/tools/tsumitate.html
A22: 免責
A23: 月次複利・利回り一定を仮定した概算です。実際の運用成果を保証するものではなく、金融商品には価格変動リスクがあります。

Sheet 年間俯瞰
A1: 年間俯瞰 — くらしの計算室
A2: ※ 各月は手取り試算・家計サマリの月次値を固定で反映しています。ボーナス月の変動は簡略化しています（年間ボーナスは下記参考欄）。
A4: 毎月の手取り（参照） | B4: ='手取り試算'!B17 | D4: 年間ボーナス（参考） | E4: ='手取り試算'!B4
A5: 毎月の支出（参照） | B5: ='家計サマリ'!B22
A6: 毎月の貯蓄（参照） | B6: ='家計サマリ'!B23
A8: 月 | B8: 手取り | C8: 支出 | D8: 貯蓄 | E8: 累計貯蓄
A9: 1月 | B9: =$B$4 | C9: =$B$5 | D9: =$B$6 | E9: =D9
A10: 2月 | B10: =$B$4 | C10: =$B$5 | D10: =$B$6 | E10: =E9+D10
A11: 3月 | B11: =$B$4 | C11: =$B$5 | D11: =$B$6 | E11: =E10+D11
A12: 4月 | B12: =$B$4 | C12: =$B$5 | D12: =$B$6 | E12: =E11+D12
A13: 5月 | B13: =$B$4 | C13: =$B$5 | D13: =$B$6 | E13: =E12+D13
A14: 6月 | B14: =$B$4 | C14: =$B$5 | D14: =$B$6 | E14: =E13+D14
A15: 7月 | B15: =$B$4 | C15: =$B$5 | D15: =$B$6 | E15: =E14+D15
A16: 8月 | B16: =$B$4 | C16: =$B$5 | D16: =$B$6 | E16: =E15+D16
A17: 9月 | B17: =$B$4 | C17: =$B$5 | D17: =$B$6 | E17: =E16+D17
A18: 10月 | B18: =$B$4 | C18: =$B$5 | D18: =$B$6 | E18: =E17+D18
A19: 11月 | B19: =$B$4 | C19: =$B$5 | D19: =$B$6 | E19: =E18+D19
A20: 12月 | B20: =$B$4 | C20: =$B$5 | D20: =$B$6 | E20: =E19+D20
A21: 年間合計 | B21: =SUM(B9:B20) | C21: =SUM(C9:C20) | D21: =SUM(D9:D20) | E21: =E20
A23: 年間サマリ
A24: 年間貯蓄率 | B24: =IF(B21=0,"",D21/B21)
A25: 月平均手取り | B25: =B21/12
A26: 月平均支出 | B26: =C21/12
A27: 月平均貯蓄 | B27: =D21/12
